src/whisper_ctranslate2/audio.py
src/whisper_ctranslate2/commandline.py
src/whisper_ctranslate2/diarization.py
src/whisper_ctranslate2/exit_code.py
src/whisper_ctranslate2/languages.py
src/whisper_ctranslate2/live.py
src/whisper_ctranslate2/live_old.py
src/whisper_ctranslate2/livetest.py
src/whisper_ctranslate2/transcribe.py
src/whisper_ctranslate2/version.py
src/whisper_ctranslate2/whisper_ctranslate2.py
src/whisper_ctranslate2/writers.py
whisper_ctranslate2/__init__.py
whisper_ctranslate2/commandline.py
whisper_ctranslate2/diarization.py
whisper_ctranslate2/exit_code.py
whisper_ctranslate2/languages.py
whisper_ctranslate2/live.py
whisper_ctranslate2/transcribe.py
whisper_ctranslate2/version.py
whisper_ctranslate2/whisper_ctranslate2.py
whisper_ctranslate2/writers.py
whisper_ctranslate2-0.5.6.dist-info/licenses/LICENSE
whisper_ctranslate2-0.5.6.dist-info/METADATA
whisper_ctranslate2-0.5.6.dist-info/WHEEL
whisper_ctranslate2-0.5.6.dist-info/entry_points.txt
whisper_ctranslate2-0.5.6.dist-info/top_level.txt
whisper_ctranslate2-0.5.6.dist-info/RECORD
