Metadata-Version: 2.4
Name: whisper-ctranslate2
Version: 0.5.6
Summary: Whisper command line client that uses CTranslate2 and faster-whisper
Home-page: https://github.com/Softcatala/whisper-ctranslate2
Author: Jordi Mas
Author-email: jmas@softcatala.org
License: MIT
Classifier: License :: OSI Approved :: MIT License
Classifier: Programming Language :: Python :: 3.6
Classifier: Programming Language :: Python :: 3.7
Classifier: Programming Language :: Python :: 3.8
Classifier: Programming Language :: Python :: 3.9
Classifier: Programming Language :: Python :: 3.10
Classifier: Programming Language :: Python :: 3.11
Classifier: Programming Language :: Python :: 3.12
Classifier: Programming Language :: Python :: 3.13
Classifier: Programming Language :: Python :: 3.14
Classifier: Topic :: Scientific/Engineering :: Artificial Intelligence
License-File: LICENSE
Requires-Dist: numpy
Requires-Dist: faster-whisper>=1.2.0
Requires-Dist: ctranslate2
Requires-Dist: tqdm
Requires-Dist: sounddevice
Requires-Dist: numpy
Provides-Extra: dev
Requires-Dist: flake8==7.*; extra == "dev"
Requires-Dist: black==24.*; extra == "dev"
Requires-Dist: isort==5.13; extra == "dev"
Requires-Dist: nose2; extra == "dev"
Requires-Dist: twine; extra == "dev"
Dynamic: author
Dynamic: author-email
Dynamic: classifier
Dynamic: description
Dynamic: description-content-type
Dynamic: home-page
Dynamic: license
Dynamic: license-file
Dynamic: provides-extra
Dynamic: requires-dist
Dynamic: summary
